SynthShapes/__init__.py
SynthShapes/blending.py
SynthShapes/filters.py
SynthShapes/hist.py
SynthShapes/shapes.py
SynthShapes/texturizing.py
SynthShapes/utils.py
SynthShapes-0.1.5.dist-info/METADATA
SynthShapes-0.1.5.dist-info/WHEEL
SynthShapes-0.1.5.dist-info/top_level.txt
SynthShapes-0.1.5.dist-info/RECORD
