Metadata-Version: 2.1
Name: SynthShapes
Version: 0.1.5
Summary: A 3D shape generator implemented in pure pytorch for biomedical image augmentation.
Author: Etienne Chollet
Author-email: etiennepchollet@gmail.com
Classifier: Development Status :: 4 - Beta
Classifier: Intended Audience :: Science/Research
Classifier: Topic :: Software Development :: Build Tools
Classifier: License :: OSI Approved :: MIT License
Classifier: Programming Language :: Python :: 3.9
Requires-Python: ~=3.9
Requires-Dist: cupy-cuda116
Requires-Dist: torch
Requires-Dist: torchvision
Requires-Dist: torchaudio
Requires-Dist: torchmetrics
Requires-Dist: matplotlib
Requires-Dist: cornucopia
Requires-Dist: nibabel
